firstdemolpackage/__init__.py
firstdemolpackage/jisuan.py
firstdemolpackage/math.py
firstdemolpackage-0.0.2.dist-info/METADATA
firstdemolpackage-0.0.2.dist-info/WHEEL
firstdemolpackage-0.0.2.dist-info/top_level.txt
firstdemolpackage-0.0.2.dist-info/RECORD
