Metadata-Version: 2.1
Name: firstdemolpackage
Version: 0.0.2
Summary: 打包测试
Home-page: http://www.baidu.com
Author: ken
Author-email: xiaomishaona@126.com
Maintainer: ken
Maintainer-email: xiaomishaona@126.com
License: BSD License
Platform: all
Classifier: Development Status :: 4 - Beta
Classifier: Operating System :: OS Independent
Classifier: Intended Audience :: Developers
Classifier: License :: OSI Approved :: BSD License
Classifier: Programming Language :: Python :: 3
Classifier: Topic :: Software Development :: Libraries
Requires-Dist: requests-html
Requires-Dist: six (>=1.5.2)
